Classfile /C:/Users/fxb20/git/margo-java-base/margo-jvm/target/classes/com/margo/project/jvm/polymorphism/StaticDispatch.class
  Last modified 2022-4-30; size 1638 bytes
  MD5 checksum 0f54ab4929208ea2600bcc070aecb3ad
  Compiled from "StaticDispatch.java"
public class com.margo.project.jvm.polymorphism.StaticDispatch
  minor version: 0
  major version: 52
  flags: ACC_PUBLIC, ACC_SUPER
Constant pool:
   #1 = Class              #2             // com/margo/project/jvm/polymorphism/StaticDispatch
   #2 = Utf8               com/margo/project/jvm/polymorphism/StaticDispatch
   #3 = Class              #4             // java/lang/Object
   #4 = Utf8               java/lang/Object
   #5 = Utf8               <init>
   #6 = Utf8               ()V
   #7 = Utf8               Code
   #8 = Methodref          #3.#9          // java/lang/Object."<init>":()V
   #9 = NameAndType        #5:#6          // "<init>":()V
  #10 = Utf8               LineNumberTable
  #11 = Utf8               LocalVariableTable
  #12 = Utf8               this
  #13 = Utf8               Lcom/margo/project/jvm/polymorphism/StaticDispatch;
  #14 = Utf8               sayHello
  #15 = Utf8               (Lcom/margo/project/jvm/polymorphism/StaticDispatch$Human;)V
  #16 = Fieldref           #17.#19        // java/lang/System.out:Ljava/io/PrintStream;
  #17 = Class              #18            // java/lang/System
  #18 = Utf8               java/lang/System
  #19 = NameAndType        #20:#21        // out:Ljava/io/PrintStream;
  #20 = Utf8               out
  #21 = Utf8               Ljava/io/PrintStream;
  #22 = String             #23            // hello,guy!
  #23 = Utf8               hello,guy!
  #24 = Methodref          #25.#27        // java/io/PrintStream.println:(Ljava/lang/String;)V
  #25 = Class              #26            // java/io/PrintStream
  #26 = Utf8               java/io/PrintStream
  #27 = NameAndType        #28:#29        // println:(Ljava/lang/String;)V
  #28 = Utf8               println
  #29 = Utf8               (Ljava/lang/String;)V
  #30 = Utf8               guy
  #31 = Utf8               Lcom/margo/project/jvm/polymorphism/StaticDispatch$Human;
  #32 = Utf8               (Lcom/margo/project/jvm/polymorphism/StaticDispatch$Man;)V
  #33 = String             #34            // hello,gentleman!
  #34 = Utf8               hello,gentleman!
  #35 = Utf8               Lcom/margo/project/jvm/polymorphism/StaticDispatch$Man;
  #36 = Utf8               (Lcom/margo/project/jvm/polymorphism/StaticDispatch$Woman;)V
  #37 = String             #38            // hello,lady!
  #38 = Utf8               hello,lady!
  #39 = Utf8               Lcom/margo/project/jvm/polymorphism/StaticDispatch$Woman;
  #40 = Utf8               main
  #41 = Utf8               ([Ljava/lang/String;)V
  #42 = Class              #43            // com/margo/project/jvm/polymorphism/StaticDispatch$Man
  #43 = Utf8               com/margo/project/jvm/polymorphism/StaticDispatch$Man
  #44 = Methodref          #42.#9         // com/margo/project/jvm/polymorphism/StaticDispatch$Man."<init>":()V
  #45 = Class              #46            // com/margo/project/jvm/polymorphism/StaticDispatch$Woman
  #46 = Utf8               com/margo/project/jvm/polymorphism/StaticDispatch$Woman
  #47 = Methodref          #45.#9         // com/margo/project/jvm/polymorphism/StaticDispatch$Woman."<init>":()V
  #48 = Methodref          #1.#9          // com/margo/project/jvm/polymorphism/StaticDispatch."<init>":()V
  #49 = Methodref          #1.#50         // com/margo/project/jvm/polymorphism/StaticDispatch.sayHello:(Lcom/margo/project/jvm/polymorphism/StaticDispatch$Human;)V
  #50 = NameAndType        #14:#15        // sayHello:(Lcom/margo/project/jvm/polymorphism/StaticDispatch$Human;)V
  #51 = Utf8               args
  #52 = Utf8               [Ljava/lang/String;
  #53 = Utf8               man
  #54 = Utf8               woman
  #55 = Utf8               sr
  #56 = Utf8               SourceFile
  #57 = Utf8               StaticDispatch.java
  #58 = Utf8               InnerClasses
  #59 = Class              #60            // com/margo/project/jvm/polymorphism/StaticDispatch$Human
  #60 = Utf8               com/margo/project/jvm/polymorphism/StaticDispatch$Human
  #61 = Utf8               Human
  #62 = Utf8               Man
  #63 = Utf8               Woman
{
  public com.margo.project.jvm.polymorphism.StaticDispatch();
    descriptor: ()V
    flags: ACC_PUBLIC
    Code:
      stack=1, locals=1, args_size=1
         0: aload_0
         1: invokespecial #8                  // Method java/lang/Object."<init>":()V
         4: return
      LineNumberTable:
        line 8: 0
      LocalVariableTable:
        Start  Length  Slot  Name   Signature
            0       5     0  this   Lcom/margo/project/jvm/polymorphism/StaticDispatch;

  public void sayHello(com.margo.project.jvm.polymorphism.StaticDispatch$Human);
    descriptor: (Lcom/margo/project/jvm/polymorphism/StaticDispatch$Human;)V
    flags: ACC_PUBLIC
    Code:
      stack=2, locals=2, args_size=2
         0: getstatic     #16                 // Field java/lang/System.out:Ljava/io/PrintStream;
         3: ldc           #22                 // String hello,guy!
         5: invokevirtual #24                 // Method java/io/PrintStream.println:(Ljava/lang/String;)V
         8: return
      LineNumberTable:
        line 23: 0
        line 24: 8
      LocalVariableTable:
        Start  Length  Slot  Name   Signature
            0       9     0  this   Lcom/margo/project/jvm/polymorphism/StaticDispatch;
            0       9     1   guy   Lcom/margo/project/jvm/polymorphism/StaticDispatch$Human;

  public void sayHello(com.margo.project.jvm.polymorphism.StaticDispatch$Man);
    descriptor: (Lcom/margo/project/jvm/polymorphism/StaticDispatch$Man;)V
    flags: ACC_PUBLIC
    Code:
      stack=2, locals=2, args_size=2
         0: getstatic     #16                 // Field java/lang/System.out:Ljava/io/PrintStream;
         3: ldc           #33                 // String hello,gentleman!
         5: invokevirtual #24                 // Method java/io/PrintStream.println:(Ljava/lang/String;)V
         8: return
      LineNumberTable:
        line 27: 0
        line 28: 8
      LocalVariableTable:
        Start  Length  Slot  Name   Signature
            0       9     0  this   Lcom/margo/project/jvm/polymorphism/StaticDispatch;
            0       9     1   guy   Lcom/margo/project/jvm/polymorphism/StaticDispatch$Man;

  public void sayHello(com.margo.project.jvm.polymorphism.StaticDispatch$Woman);
    descriptor: (Lcom/margo/project/jvm/polymorphism/StaticDispatch$Woman;)V
    flags: ACC_PUBLIC
    Code:
      stack=2, locals=2, args_size=2
         0: getstatic     #16                 // Field java/lang/System.out:Ljava/io/PrintStream;
         3: ldc           #37                 // String hello,lady!
         5: invokevirtual #24                 // Method java/io/PrintStream.println:(Ljava/lang/String;)V
         8: return
      LineNumberTable:
        line 31: 0
        line 32: 8
      LocalVariableTable:
        Start  Length  Slot  Name   Signature
            0       9     0  this   Lcom/margo/project/jvm/polymorphism/StaticDispatch;
            0       9     1   guy   Lcom/margo/project/jvm/polymorphism/StaticDispatch$Woman;

  public static void main(java.lang.String[]);
    descriptor: ([Ljava/lang/String;)V
    flags: ACC_PUBLIC, ACC_STATIC
    Code:
      stack=2, locals=4, args_size=1
         0: new           #42                 // class com/margo/project/jvm/polymorphism/StaticDispatch$Man
         3: dup
         4: invokespecial #44                 // Method com/margo/project/jvm/polymorphism/StaticDispatch$Man."<init>":()V
         7: astore_1
         8: new           #45                 // class com/margo/project/jvm/polymorphism/StaticDispatch$Woman
        11: dup
        12: invokespecial #47                 // Method com/margo/project/jvm/polymorphism/StaticDispatch$Woman."<init>":()V
        15: astore_2
        16: new           #1                  // class com/margo/project/jvm/polymorphism/StaticDispatch
        19: dup
        20: invokespecial #48                 // Method "<init>":()V
        23: astore_3
        24: aload_3
        25: aload_1
        26: invokevirtual #49                 // Method sayHello:(Lcom/margo/project/jvm/polymorphism/StaticDispatch$Human;)V
        29: aload_3
        30: aload_2
        31: invokevirtual #49                 // Method sayHello:(Lcom/margo/project/jvm/polymorphism/StaticDispatch$Human;)V
        34: return
      LineNumberTable:
        line 35: 0
        line 36: 8
        line 37: 16
        line 38: 24
        line 39: 29
        line 40: 34
      LocalVariableTable:
        Start  Length  Slot  Name   Signature
            0      35     0  args   [Ljava/lang/String;
            8      27     1   man   Lcom/margo/project/jvm/polymorphism/StaticDispatch$Human;
           16      19     2 woman   Lcom/margo/project/jvm/polymorphism/StaticDispatch$Human;
           24      11     3    sr   Lcom/margo/project/jvm/polymorphism/StaticDispatch;
}
SourceFile: "StaticDispatch.java"
InnerClasses:
     static abstract #61= #59 of #1; //Human=class com/margo/project/jvm/polymorphism/StaticDispatch$Human of class com/margo/project/jvm/polymorphism/StaticDispatch
     static #62= #42 of #1; //Man=class com/margo/project/jvm/polymorphism/StaticDispatch$Man of class com/margo/project/jvm/polymorphism/StaticDispatch
     static #63= #45 of #1; //Woman=class com/margo/project/jvm/polymorphism/StaticDispatch$Woman of class com/margo/project/jvm/polymorphism/StaticDispatch
